LICENSE
MANIFEST.in
README.md
setup.cfg
setup.py
docassemble.LAWVExpungementEvaluator.egg-info/PKG-INFO
docassemble.LAWVExpungementEvaluator.egg-info/SOURCES.txt
docassemble.LAWVExpungementEvaluator.egg-info/dependency_links.txt
docassemble.LAWVExpungementEvaluator.egg-info/not-zip-safe
docassemble.LAWVExpungementEvaluator.egg-info/requires.txt
docassemble.LAWVExpungementEvaluator.egg-info/top_level.txt
docassemble/LAWVExpungementEvaluator/__init__.py
docassemble/LAWVExpungementEvaluator/data/questions/expungement_evaluation.yml
docassemble/LAWVExpungementEvaluator/data/questions/statutes.yml
docassemble/LAWVExpungementEvaluator/data/sources/README.md
docassemble/LAWVExpungementEvaluator/data/static/README.md
docassemble/LAWVExpungementEvaluator/data/static/dismissed_plea.png
docassemble/LAWVExpungementEvaluator/data/templates/README.md
docassemble/LAWVExpungementEvaluator/data/templates/worksheet.pdf